{
    "search_button": "Nei Sich",
    "review_question": "Wéi hunn mir ët gemaach?",
    "leave_review": "Lass e Review do",
    "review": "Review",
    "phone": "Telefon",
    "homepage": "Homepage",
    "from": "Vu",
    "to": "Zu",
    "expected_delivery_date": "Erwartete Liferungsdatum",
    "last_updated": "Lescht Aktualiséierung",
    "show_details": "Weisen Detailer",
    "hide_details": "Verstoppen Detailer",
    "review_parcel": "Rezenséieren Paket",
    "carrier_review_title": "Wéi zefridden sidd Dir mam Carrier Service?",
    "product_review_title": "Wéi zefridden sidd Dir mam Produkt?",
    "package_review_title": "Wéi zefridden sidd Dir mam Verpackungs-Qualitéit?",
    "review_required_message": "Bidden Iech, looss Är Rezensioun!",
    "comments": "Commentairen",
    "connents_required_message": "Bidden Iech, schreiwen den Commentaire!",
    "overall_rating": "Allgemeng Bewertung",
    "submit_review": "Rezensioun ofschécken",
    "search_title": "Gitt w.e.g. Ären Trackingnummer, Är Bestellnummer oder Är E-Mail an a kritt Trackingresultater.",
    "search_input_placeholder": "Gitt w.e.g. Ären Trackingnummer, Är Bestellnummer oder Är E-Mail an",
    "track_button": "Tracken",
    "back_to_search_button": "Zréck zur Sich",
    "no_info": "Keng Informatiounen",
    "pre_transit": "Vir-Transit",
    "delivery_in_progress": "Leverung an Ausféierung",
    "in_transit": "Am Transport",
    "customs_clearance": "Douaneclaratioun",
    "return_to_sender": "Zréck zum Empfänger",
    "expired": "Abgelaaf",
    "transit_limit_exceeded": "Transit Limit iwwerschratt",
    "unsuccessful_delivery": "Dëstellverkéierung net erfollegräich",
    "error": "Fehler",
    "exception": "Ausnahm",
    "cancelled": "Ofgesot",
    "delivered": "Gelafert",
    "available_for_pickup": "Verfügbar",
    "description_no_info": "Et gouf eng Versandsëtze erstallt, mee d'Pak wéi nach net gescannt a/oder vum Paketedénger ofgeholl gouf.",
    "description_pre_transit": "Carrier huet Informatiounen iwwer d'Paket kritt, awer et gouf nach net gescannt a opgeholl.",
    "description_delivery_in_progress": "D'Paket huet d'Regioun erreicht a gouf am Gank vu geléiert ginn.",
    "description_in_transit": "D'Paket ass ënnerwee zu senger Zil. Dir kënnt méi wéi eng Update vun dësem Typ kréien, wa s'Paket ënnerwee ass.",
    "description_customs_clearance": "Äre Paket gëtt vun der Douane verarbeit. Falls néideg, kënnt Dir kontaktéiert ginn fir zousätzlech Dokumentatioun, Informatiounen oder Zuelungen vu Douanen- / Steieren ze maachen. Si wäert schnell op Är Nofro reagéieren.",
    "description_return_to_sender": "D'Paket gouf net ausgeléiert an ass elo op dem Wee zréck zum Versender.",
    "description_expired": "D'Paket huet keng Tracking-Informatiounen an de leschte 30 Deeg zougänglech gehat, säit et erstallt gouf.",
    "description_transit_limit_exceeded": "D'Paket ass wäit méi laang am Transit wéi normale Transit-Zäit erlaabt. W.e.g. kontaktéiert den Carrier.",
    "description_unsuccessful_delivery": "De Carrier huet probéiert ze liefern, mee et ass net gelongen. Hien hënnerléisst normalerweis eng Notiz a probéiert, sech erëm ze mellen.",
    "description_error": "Et ass net méiglech, dëse Paket ze verfollegen wéinst technesche Problemer. W.e.g. spéider nach eng Kéier verfollegen.",
    "description_exception": "Douane Halen oder aner Ausnamen am Versand. W.e.g. kontaktéiert den Carrier.",
    "description_cancelled": "D'Lieferung ass ofgesot ginn.",
    "description_delivered": "D'Pakéit ass geluecht ginn.",
    "description_available_for_pickup": "D'Pakéit ass fir Ofhuele vum Carrier sengem Gebai disponibel.",
    "powered_by": "Betriwwe vun",
    "sidebar_show_more": "Méi weisen",
    "no_numbers": "Keng Informatioun fonnt. <br /> Versicht et nach eng Kéier mat de korrekten Donnéeen oder kontaktéier de Kundeservice.",
    "no_trackings": "Nach näischt :) <br> Är Pakéiten wäerten hei ugewisen ginn <br> soubald se verschéckt sinn.",
    "order_number": "Bestellungsnimm",
    "tracking_number": "Tracking-Nimm",
    "email": "Email",
    "last_update": "Lescht Aktualiséierung",
    "btn_hide_products": "Produkter verstoppen",
    "tp_not_yet_fulfilled": "Echternach nit gescheckt",
    "tp_qty": "Quantitéit",
    "tp_total": "Total",
    "tp_price": "Präis",
    "btn_show_products": "Produkter weisen"
}